tapioca_braspag/__init__.py
tapioca_braspag/resource_mapping.py
tapioca_braspag/tapioca_braspag.py
tapioca_braspag-0.3.dist-info/DESCRIPTION.rst
tapioca_braspag-0.3.dist-info/METADATA
tapioca_braspag-0.3.dist-info/RECORD
tapioca_braspag-0.3.dist-info/WHEEL
tapioca_braspag-0.3.dist-info/metadata.json
tapioca_braspag-0.3.dist-info/top_level.txt
