Metadata-Version: 2.0
Name: tapioca-braspag
Version: 0.3
Summary: Braspag API wrapper using tapioca
Home-page: https://github.com/parafernalia/tapioca-braspag
Author: Rômulo Collopy, Diego Dukão
Author-email: romulocollopy@gmail.com
License: MIT
Keywords: braspag
Platform: UNKNOWN
Classifier: Development Status :: 5 - Production/Stable
Classifier: Intended Audience :: Developers
Classifier: License :: OSI Approved :: MIT License
Classifier: Natural Language :: English
Classifier: Programming Language :: Python :: 2
Classifier: Programming Language :: Python :: 2.7
Classifier: Programming Language :: Python :: 3
Classifier: Programming Language :: Python :: 3.1
Classifier: Programming Language :: Python :: 3.2
Classifier: Programming Language :: Python :: 3.3
Classifier: Programming Language :: Python :: 3.4
Classifier: Programming Language :: Python :: 3.5
Requires-Dist: tapioca-wrapper (<0.6.0)
